{
    "electronics": {
        "name": "Elektronik",
        "conditions": ["Neu", "Gebraucht", "Refurbished", "Defekt", "Wie neu", "Geöffnet, unbenutzt"],
        "extra": ["Garantie", "Modellnummer", "Zubehör", "Originalverpackung", "Baujahr", "Hersteller"],
        "color": "var(--category-electronics)"
    },
    "clothing": {
        "name": "Kleidung",
        "conditions": ["Neu mit Etikett", "Neu ohne Etikett", "Sehr gut", "Gut", "Akzeptabel", "Ungetragen", "Leichte Gebrauchsspuren"],
        "extra": ["Größe", "Material", "Marke", "Farbe", "Saison", "Geschlecht", "Stil"],
        "color": "var(--category-clothing)"
    },
    "bike": {
        "name": "Fahrrad",
        "conditions": ["Neu", "Gebraucht", "Restauriert", "Vintage", "Unfallfrei", "Mit Zubehör"],
        "extra": ["Rahmengröße", "Modell", "Marke", "Baujahr", "Farbe", "Typ", "Gangschaltung"],
        "color": "var(--category-bike)"
    },
    "furniture": {
        "name": "Möbel",
        "conditions": ["Neu", "Gebraucht", "Antik", "Restauriert", "Wie neu"],
        "extra": ["Material", "Farbe", "Maße", "Marke", "Stil", "Montagezustand"],
        "color": "var(--category-furniture)"
    },
    "books": {
        "name": "Bücher",
        "conditions": ["Neu", "Gebraucht", "Wie neu", "Mit Widmung", "Antik"],
        "extra": ["Autor", "Genre", "Sprache", "Erscheinungsjahr", "ISBN"],
        "color": "var(--category-books)"
    },
    "toys": {
        "name": "Spielzeug",
        "conditions": ["Neu", "Gebraucht", "Wie neu", "Unbenutzt"],
        "extra": ["Altersempfehlung", "Marke", "Material", "Thema"],
        "color": "var(--category-toys)"
    },
    "sports": {
        "name": "Sport & Freizeit",
        "conditions": ["Neu", "Gebraucht", "Wie neu"],
        "extra": ["Typ", "Marke", "Größe", "Zubehör"],
        "color": "var(--category-sports)"
    },
    "vehicles": {
        "name": "Fahrzeuge",
        "conditions": ["Neu", "Gebraucht", "Unfallfrei", "Bastlerfahrzeug"],
        "extra": ["Marke", "Modell", "Baujahr", "Kilometerstand", "Farbe", "Kraftstoffart"],
        "color": "var(--category-vehicles)"
    },
    "garden": {
        "name": "Garten",
        "conditions": ["Neu", "Gebraucht", "Wie neu"],
        "extra": ["Typ", "Material", "Marke", "Maße"],
        "color": "var(--category-garden)"
    },
    "other": {
        "name": "Sonstiges",
        "conditions": ["Neu", "Gebraucht", "Antik", "Sammlerstück", "Unbenutzt"],
        "extra": ["Besonderheiten", "Kategorie", "Beschreibung"],
        "color": "var(--category-other)"
    }
}
